zadarapy/__init__.py
zadarapy/session.py
zadarapy/validators.py
zadarapy/bin/__init__.py
zadarapy/bin/command_line.py
zadarapy/command_center/__init__.py
zadarapy/command_center/cloud.py
zadarapy/command_center/vpsa.py
zadarapy/command_center/vpsaos.py
zadarapy/command_center/zios.py
zadarapy/provisioning_portal/__init__.py
zadarapy/provisioning_portal/authentication.py
zadarapy/provisioning_portal/cloud.py
zadarapy/provisioning_portal/providers.py
zadarapy/provisioning_portal/requests.py
zadarapy/provisioning_portal/virtual_networks.py
zadarapy/provisioning_portal/vpsa.py
zadarapy/provisioning_portal/zios.py
zadarapy/vpsa/__init__.py
zadarapy/vpsa/antivirus.py
zadarapy/vpsa/container_services.py
zadarapy/vpsa/controllers.py
zadarapy/vpsa/drives.py
zadarapy/vpsa/logs.py
zadarapy/vpsa/mirrors.py
zadarapy/vpsa/nas_authentication.py
zadarapy/vpsa/pools.py
zadarapy/vpsa/raid_groups.py
zadarapy/vpsa/remote_clone.py
zadarapy/vpsa/remote_object_storage.py
zadarapy/vpsa/servers.py
zadarapy/vpsa/settings.py
zadarapy/vpsa/snapshot_policies.py
zadarapy/vpsa/tickets.py
zadarapy/vpsa/volumes.py
zadarapy/vpsa/vpsa_users.py
zadarapy/vpsaos/__init__.py
zadarapy/vpsaos/accounts.py
zadarapy/vpsaos/container.py
zadarapy/vpsaos/controllers.py
zadarapy/vpsaos/drives.py
zadarapy/vpsaos/load_balancer.py
zadarapy/vpsaos/logs.py
zadarapy/vpsaos/policies.py
zadarapy/vpsaos/request.py
zadarapy/vpsaos/settings.py
zadarapy/vpsaos/users.py
zadarapy/vpsaos/virtual_controller.py
zadarapy-0.77.dist-info/DESCRIPTION.rst
zadarapy-0.77.dist-info/METADATA
zadarapy-0.77.dist-info/RECORD
zadarapy-0.77.dist-info/WHEEL
zadarapy-0.77.dist-info/entry_points.txt
zadarapy-0.77.dist-info/metadata.json
zadarapy-0.77.dist-info/top_level.txt
