Metadata-Version: 2.0
Name: zadarapy
Version: 0.77
Summary: Python module and command line interface with Zadara REST APIs
Home-page: https://github.com/zadarastorage/zadarapy
Author: Jeremy Brown
Author-email: jeremy@zadarastorage.com
License: Apache License 2.0
Platform: UNKNOWN
Requires-Dist: configparser (>=3.5.0)
Requires-Dist: future (>=0.15.2)
Requires-Dist: requests (>=2.2.1)
Requires-Dist: terminaltables (>=2.1.0)
